{
  "ace": "ace",
  "afr": "afr",
  "arb": "arb",
  "azj": "azj_latn",
  "bul": "bul",
  "cat": "cat",
  "ceb": "ceb",
  "ces": "ces",
  "cym": "cym",
  "dan": "dan",
  "deu": "deu_1996",
  "eng": "eng",
  "spa": "spa",
  "est": "est",
  "eus": "eus",
  "pes": "pes_1",
  "fin": "fin",
  "fra": "fra",
  "hau": "hau_NE",
  "haw": "haw",
  "hin": "hin",
  "hrv": "hrv",
  "hun": "hun",
  "ind": "ind",
  "isl": "isl",
  "ita": "ita",
  "kaz": "kaz",
  "kir": "kir",
  "lat": "lat",
  "lit": "lit",
  "lav": "lav",
  "mkd": "mkd",
  "khk": "khk",
  "nob": "nob",
  "nep": "nep",
  "nld": "nld",
  "nbl": "nbl",
  "nso": "nso",
  "pol": "pol",
  "por": "por_PT",
  "ron": "ron_2006",
  "rus": "rus",
  "slk": "slk",
  "slv": "slv",
  "som": "som",
  "als": "als",
  "srp": "srp_cyrl",
  "ssw": "ssw",
  "sot": "sot",
  "swe": "swe",
  "swh": "swh",
  "tgl": "tgl",
  "tsn": "tsn",
  "tur": "tur",
  "tso": "tso_MZ",
  "ukr": "ukr",
  "urd": "urd",
  "uzn": "uzn_cyrl",
  "ven": "ven",
  "vie": "vie",
  "xho": "xho",
  "zul": "zul"
}
